omni_cortex/__init__.py
omni_cortex/config.py
omni_cortex/dashboard.py
omni_cortex/server.py
omni_cortex/setup.py
omni_cortex/categorization/__init__.py
omni_cortex/categorization/auto_tags.py
omni_cortex/categorization/auto_type.py
omni_cortex/database/__init__.py
omni_cortex/database/connection.py
omni_cortex/database/migrations.py
omni_cortex/database/schema.py
omni_cortex/database/sync.py
omni_cortex/decay/__init__.py
omni_cortex/decay/importance.py
omni_cortex/embeddings/__init__.py
omni_cortex/embeddings/local.py
omni_cortex/models/__init__.py
omni_cortex/models/activity.py
omni_cortex/models/agent.py
omni_cortex/models/memory.py
omni_cortex/models/relationship.py
omni_cortex/models/session.py
omni_cortex/resources/__init__.py
omni_cortex/search/__init__.py
omni_cortex/search/hybrid.py
omni_cortex/search/keyword.py
omni_cortex/search/ranking.py
omni_cortex/search/semantic.py
omni_cortex/tools/__init__.py
omni_cortex/tools/activities.py
omni_cortex/tools/memories.py
omni_cortex/tools/sessions.py
omni_cortex/tools/utilities.py
omni_cortex/utils/__init__.py
omni_cortex/utils/formatting.py
omni_cortex/utils/ids.py
omni_cortex/utils/timestamps.py
omni_cortex/utils/truncation.py
omni_cortex/_bundled/hooks/post_tool_use.py
omni_cortex/_bundled/hooks/pre_tool_use.py
omni_cortex/_bundled/hooks/session_utils.py
omni_cortex/_bundled/hooks/stop.py
omni_cortex/_bundled/hooks/subagent_stop.py
omni_cortex/_bundled/hooks/user_prompt.py
omni_cortex/_bundled/dashboard/backend/.env.example
omni_cortex/_bundled/dashboard/backend/backfill_summaries.py
omni_cortex/_bundled/dashboard/backend/chat_service.py
omni_cortex/_bundled/dashboard/backend/database.py
omni_cortex/_bundled/dashboard/backend/image_service.py
omni_cortex/_bundled/dashboard/backend/logging_config.py
omni_cortex/_bundled/dashboard/backend/main.py
omni_cortex/_bundled/dashboard/backend/models.py
omni_cortex/_bundled/dashboard/backend/project_config.py
omni_cortex/_bundled/dashboard/backend/project_scanner.py
omni_cortex-1.17.3.dist-info/METADATA
omni_cortex-1.17.3.dist-info/WHEEL
omni_cortex-1.17.3.dist-info/entry_points.txt
omni_cortex-1.17.3.dist-info/licenses/LICENSE
omni_cortex-1.17.3.dist-info/RECORD
