Metadata-Version: 2.4
Name: omni-cortex
Version: 1.17.3
Summary: Give Claude Code a perfect memory - auto-logs everything, searches smartly, and gets smarter over time
Project-URL: Homepage, https://github.com/AllCytes/Omni-Cortex
Project-URL: Repository, https://github.com/AllCytes/Omni-Cortex
Project-URL: Issues, https://github.com/AllCytes/Omni-Cortex/issues
Project-URL: Documentation, https://github.com/AllCytes/Omni-Cortex#readme
Author: Tony
License-Expression: MIT
License-File: LICENSE
Keywords: ai,anthropic,claude,claude-code,llm,mcp,memory,semantic-search
Classifier: Development Status :: 4 - Beta
Classifier: Intended Audience :: Developers
Classifier: License :: OSI Approved :: MIT License
Classifier: Programming Language :: Python :: 3
Classifier: Programming Language :: Python :: 3.10
Classifier: Programming Language :: Python :: 3.11
Classifier: Programming Language :: Python :: 3.12
Classifier: Programming Language :: Python :: 3.13
Classifier: Topic :: Scientific/Engineering :: Artificial Intelligence
Classifier: Topic :: Software Development :: Libraries :: Python Modules
Requires-Python: >=3.10
Requires-Dist: claude-agent-sdk>=0.1.0
Requires-Dist: httpx>=0.25.0
Requires-Dist: mcp>=1.0.0
Requires-Dist: pydantic>=2.0.0
Requires-Dist: python-dotenv>=1.0.0
Requires-Dist: pyyaml>=6.0.0
Provides-Extra: dev
Requires-Dist: black>=23.0.0; extra == 'dev'
Requires-Dist: pytest-asyncio>=0.21.0; extra == 'dev'
Requires-Dist: pytest>=7.0.0; extra == 'dev'
Requires-Dist: ruff>=0.1.0; extra == 'dev'
Provides-Extra: semantic
Requires-Dist: numpy>=1.24.0; extra == 'semantic'
Requires-Dist: sentence-transformers>=2.2.0; extra == 'semantic'
